[{"name":"deck_string_parser","qualifiedName":"deck_string_parser","href":"deck_string_parser/deck_string_parser-library.html","type":"library","overriddenDepth":0,"packageName":"deck_string_parser","desc":"Utility functions for parsing of PTCGO/PTCGL decks"},{"name":"Card","qualifiedName":"deck_string_parser.Card","href":"deck_string_parser/Card-class.html","type":"class","overriddenDepth":0,"packageName":"deck_string_parser","desc":"","enclosedBy":{"name":"deck_string_parser","type":"library","href":"deck_string_parser/deck_string_parser-library.html"}},{"name":"Card","qualifiedName":"deck_string_parser.Card.Card","href":"deck_string_parser/Card/Card.html","type":"constructor","overriddenDepth":0,"packageName":"deck_string_parser","desc":"This represents card attributes","enclosedBy":{"name":"Card","type":"class","href":"deck_string_parser/Card-class.html"}},{"name":"name","qualifiedName":"deck_string_parser.Card.name","href":"deck_string_parser/Card/name.html","type":"property","overriddenDepth":0,"packageName":"deck_string_parser","desc":"","enclosedBy":{"name":"Card","type":"class","href":"deck_string_parser/Card-class.html"}},{"name":"quantity","qualifiedName":"deck_string_parser.Card.quantity","href":"deck_string_parser/Card/quantity.html","type":"property","overriddenDepth":0,"packageName":"deck_string_parser","desc":"","enclosedBy":{"name":"Card","type":"class","href":"deck_string_parser/Card-class.html"}},{"name":"set","qualifiedName":"deck_string_parser.Card.set","href":"deck_string_parser/Card/set.html","type":"property","overriddenDepth":0,"packageName":"deck_string_parser","desc":"","enclosedBy":{"name":"Card","type":"class","href":"deck_string_parser/Card-class.html"}},{"name":"setQuantity","qualifiedName":"deck_string_parser.Card.setQuantity","href":"deck_string_parser/Card/setQuantity.html","type":"method","overriddenDepth":0,"packageName":"deck_string_parser","desc":"","enclosedBy":{"name":"Card","type":"class","href":"deck_string_parser/Card-class.html"}},{"name":"Deck","qualifiedName":"deck_string_parser.Deck","href":"deck_string_parser/Deck-class.html","type":"class","overriddenDepth":0,"packageName":"deck_string_parser","desc":"","enclosedBy":{"name":"deck_string_parser","type":"library","href":"deck_string_parser/deck_string_parser-library.html"}},{"name":"Deck","qualifiedName":"deck_string_parser.Deck.Deck","href":"deck_string_parser/Deck/Deck.html","type":"constructor","overriddenDepth":0,"packageName":"deck_string_parser","desc":"This represents parsed-deck strings","enclosedBy":{"name":"Deck","type":"class","href":"deck_string_parser/Deck-class.html"}},{"name":"energyList","qualifiedName":"deck_string_parser.Deck.energyList","href":"deck_string_parser/Deck/energyList.html","type":"property","overriddenDepth":0,"packageName":"deck_string_parser","desc":"","enclosedBy":{"name":"Deck","type":"class","href":"deck_string_parser/Deck-class.html"}},{"name":"pokemonList","qualifiedName":"deck_string_parser.Deck.pokemonList","href":"deck_string_parser/Deck/pokemonList.html","type":"property","overriddenDepth":0,"packageName":"deck_string_parser","desc":"","enclosedBy":{"name":"Deck","type":"class","href":"deck_string_parser/Deck-class.html"}},{"name":"trainerList","qualifiedName":"deck_string_parser.Deck.trainerList","href":"deck_string_parser/Deck/trainerList.html","type":"property","overriddenDepth":0,"packageName":"deck_string_parser","desc":"","enclosedBy":{"name":"Deck","type":"class","href":"deck_string_parser/Deck-class.html"}},{"name":"Energy","qualifiedName":"deck_string_parser.Energy","href":"deck_string_parser/Energy-class.html","type":"class","overriddenDepth":0,"packageName":"deck_string_parser","desc":"","enclosedBy":{"name":"deck_string_parser","type":"library","href":"deck_string_parser/deck_string_parser-library.html"}},{"name":"Energy","qualifiedName":"deck_string_parser.Energy.Energy","href":"deck_string_parser/Energy/Energy.html","type":"constructor","overriddenDepth":0,"packageName":"deck_string_parser","desc":"This represents Energy-cards","enclosedBy":{"name":"Energy","type":"class","href":"deck_string_parser/Energy-class.html"}},{"name":"Pokemon","qualifiedName":"deck_string_parser.Pokemon","href":"deck_string_parser/Pokemon-class.html","type":"class","overriddenDepth":0,"packageName":"deck_string_parser","desc":"","enclosedBy":{"name":"deck_string_parser","type":"library","href":"deck_string_parser/deck_string_parser-library.html"}},{"name":"Pokemon","qualifiedName":"deck_string_parser.Pokemon.Pokemon","href":"deck_string_parser/Pokemon/Pokemon.html","type":"constructor","overriddenDepth":0,"packageName":"deck_string_parser","desc":"This represents Pokemon-cards","enclosedBy":{"name":"Pokemon","type":"class","href":"deck_string_parser/Pokemon-class.html"}},{"name":"Trainer","qualifiedName":"deck_string_parser.Trainer","href":"deck_string_parser/Trainer-class.html","type":"class","overriddenDepth":0,"packageName":"deck_string_parser","desc":"","enclosedBy":{"name":"deck_string_parser","type":"library","href":"deck_string_parser/deck_string_parser-library.html"}},{"name":"Trainer","qualifiedName":"deck_string_parser.Trainer.Trainer","href":"deck_string_parser/Trainer/Trainer.html","type":"constructor","overriddenDepth":0,"packageName":"deck_string_parser","desc":"This represents Trainer-cards","enclosedBy":{"name":"Trainer","type":"class","href":"deck_string_parser/Trainer-class.html"}},{"name":"isValidDeckCount","qualifiedName":"deck_string_parser.isValidDeckCount","href":"deck_string_parser/isValidDeckCount.html","type":"function","overriddenDepth":0,"packageName":"deck_string_parser","desc":"","enclosedBy":{"name":"deck_string_parser","type":"library","href":"deck_string_parser/deck_string_parser-library.html"}},{"name":"isValidDeckString","qualifiedName":"deck_string_parser.isValidDeckString","href":"deck_string_parser/isValidDeckString.html","type":"function","overriddenDepth":0,"packageName":"deck_string_parser","desc":"","enclosedBy":{"name":"deck_string_parser","type":"library","href":"deck_string_parser/deck_string_parser-library.html"}},{"name":"parseDeck","qualifiedName":"deck_string_parser.parseDeck","href":"deck_string_parser/parseDeck.html","type":"function","overriddenDepth":0,"packageName":"deck_string_parser","desc":"","enclosedBy":{"name":"deck_string_parser","type":"library","href":"deck_string_parser/deck_string_parser-library.html"}}]
